chroma/__init__.py
chroma/constants/__init__.py
chroma/constants/geometry.py
chroma/constants/named_models.py
chroma/constants/sequence.py
chroma/data/__init__.py
chroma/data/protein.py
chroma/data/system.py
chroma/data/xcs.py
chroma/layers/__init__.py
chroma/layers/attention.py
chroma/layers/basic.py
chroma/layers/complexity.py
chroma/layers/conv.py
chroma/layers/graph.py
chroma/layers/linalg.py
chroma/layers/norm.py
chroma/layers/sde.py
chroma/layers/structure/__init__.py
chroma/layers/structure/backbone.py
chroma/layers/structure/conditioners.py
chroma/layers/structure/diffusion.py
chroma/layers/structure/geometry.py
chroma/layers/structure/hbonds.py
chroma/layers/structure/mvn.py
chroma/layers/structure/optimal_transport.py
chroma/layers/structure/potts.py
chroma/layers/structure/protein_graph.py
chroma/layers/structure/protein_graph_allatom.py
chroma/layers/structure/rmsd.py
chroma/layers/structure/sidechain.py
chroma/layers/structure/symmetry.py
chroma/layers/structure/transforms.py
chroma/models/__init__.py
chroma/models/chroma.py
chroma/models/graph_backbone.py
chroma/models/graph_classifier.py
chroma/models/graph_design.py
chroma/models/graph_energy.py
chroma/models/procap.py
chroma/utility/__init__.py
chroma/utility/api.py
chroma/utility/chroma.py
chroma/utility/fetchdb.py
chroma/utility/model.py
chroma/utility/ngl.py
chroma/utility/polyseq.py
chroma/utility/starparser.py
tests/__init__.py
tests/conftest.py
tests/data/__init__.py
tests/data/test_protein.py
tests/data/test_system.py
tests/layers/__init__.py
tests/layers/test_basic.py
tests/layers/test_graph.py
tests/layers/test_norm.py
tests/layers/test_sde.py
tests/layers/structure/__init__.py
tests/layers/structure/test_backbone.py
tests/layers/structure/test_conditioners.py
tests/layers/structure/test_diffusion.py
tests/layers/structure/test_geometry.py
tests/layers/structure/test_hbonds.py
tests/layers/structure/test_mvn.py
tests/layers/structure/test_optimal_transport.py
generate_chroma-1.0.0.dist-info/LICENSE.txt
generate_chroma-1.0.0.dist-info/METADATA
generate_chroma-1.0.0.dist-info/WHEEL
generate_chroma-1.0.0.dist-info/top_level.txt
generate_chroma-1.0.0.dist-info/RECORD
